danceschool/__init__.py
danceschool/default_settings.py
danceschool/setup.cfg
danceschool/urls.py
danceschool/__pycache__/__init__.cpython-35.pyc
danceschool/__pycache__/__init__.cpython-36.pyc
danceschool/__pycache__/default_settings.cpython-35.pyc
danceschool/__pycache__/default_settings.cpython-36.pyc
danceschool/__pycache__/urls.cpython-35.pyc
danceschool/__pycache__/urls.cpython-36.pyc
danceschool/backups/__init__.py
danceschool/backups/apps.py
danceschool/backups/dynamic_preferences_registry.py
danceschool/backups/tasks.py
danceschool/backups/management/__init__.py
danceschool/backups/management/commands/backup_now.py
danceschool/banlist/__init__.py
danceschool/banlist/admin.py
danceschool/banlist/apps.py
danceschool/banlist/cms_toolbars.py
danceschool/banlist/dynamic_preferences_registry.py
danceschool/banlist/handlers.py
danceschool/banlist/models.py
danceschool/banlist/urls.py
danceschool/banlist/views.py
danceschool/banlist/__pycache__/__init__.cpython-35.pyc
danceschool/banlist/__pycache__/__init__.cpython-36.pyc
danceschool/banlist/__pycache__/admin.cpython-35.pyc
danceschool/banlist/__pycache__/admin.cpython-36.pyc
danceschool/banlist/__pycache__/apps.cpython-35.pyc
danceschool/banlist/__pycache__/apps.cpython-36.pyc
danceschool/banlist/__pycache__/cms_toolbars.cpython-36.pyc
danceschool/banlist/__pycache__/dynamic_preferences_registry.cpython-35.pyc
danceschool/banlist/__pycache__/dynamic_preferences_registry.cpython-36.pyc
danceschool/banlist/__pycache__/handlers.cpython-35.pyc
danceschool/banlist/__pycache__/handlers.cpython-36.pyc
danceschool/banlist/__pycache__/models.cpython-35.pyc
danceschool/banlist/__pycache__/models.cpython-36.pyc
danceschool/banlist/__pycache__/urls.cpython-35.pyc
danceschool/banlist/__pycache__/urls.cpython-36.pyc
danceschool/banlist/__pycache__/views.cpython-35.pyc
danceschool/banlist/__pycache__/views.cpython-36.pyc
danceschool/banlist/migrations/0001_initial.py
danceschool/banlist/migrations/0002_auto_20181114_2144.py
django_danceschool-0.9.3.dist-info/LICENSE
django_danceschool-0.9.3.dist-info/METADATA
django_danceschool-0.9.3.dist-info/PKG-INFO-CONFLICT-1
django_danceschool-0.9.3.dist-info/WHEEL
django_danceschool-0.9.3.dist-info/requires-CONFLICT-1.txt
django_danceschool-0.9.3.dist-info/top_level.txt
django_danceschool-0.9.3.dist-info/RECORD
