Metadata-Version: 2.1
Name: django-danceschool
Version: 0.9.3
Summary: The Django Dance School project: a modular, reusable set of designed to integrate all of the regular functions of a social dance school with the Django CMS content management system
Home-page: https://github.com/django-danceschool/django-danceschool
Author: Lee Tucker
Author-email: lee.c.tucker@gmail.com
License: BSD License
Platform: UNKNOWN
Classifier: Environment :: Web Environment
Classifier: Framework :: Django
Classifier: Intended Audience :: Developers
Classifier: License :: OSI Approved :: BSD License
Classifier: Operating System :: OS Independent
Classifier: Programming Language :: Python
Classifier: Programming Language :: Python :: 3.4
Classifier: Programming Language :: Python :: 3.5
Classifier: Topic :: Internet :: WWW/HTTP
Classifier: Topic :: Internet :: WWW/HTTP :: Dynamic Content
Requires-Dist: Django (<3.2,>=3.1.6)
Requires-Dist: Pillow (>=3.4.2)
Requires-Dist: beautifulsoup4 (>=4.6.0)
Requires-Dist: django-admin-rangefilter (>=0.6.4)
Requires-Dist: django-admin-sortable2 (>=0.7.2)
Requires-Dist: django-allauth (>=0.31.0)
Requires-Dist: django-autocomplete-light (>=3.8.2)
Requires-Dist: django-braces (>=1.8.1)
Requires-Dist: django-ckeditor-filebrowser-filer (>=0.3.0)
Requires-Dist: django-ckeditor (>=5.4.0)
Requires-Dist: django-cms (>=3.8.0)
Requires-Dist: django-colorful (>=1.2)
Requires-Dist: django-crispy-forms (>=1.6.0)
Requires-Dist: django-dynamic-preferences (>=1.8.1)
Requires-Dist: django-easy-pdf (>=0.1.1)
Requires-Dist: django-filer (>=1.7.0)
Requires-Dist: django-ical (>=1.4)
Requires-Dist: django-imagekit (>=3.3)
Requires-Dist: django-multiselectfield (>=0.1.5)
Requires-Dist: django-polymorphic (>=3.0.0)
Requires-Dist: django-sekizai (>=0.10.0)
Requires-Dist: django-utils-six (>=2.0)
Requires-Dist: djangocms-admin-style (>=1.2.6.2)
Requires-Dist: djangocms-bootstrap4 (>=1.3.1)
Requires-Dist: djangocms-icon (>=1.3.0)
Requires-Dist: djangocms-link (>=2.3.1)
Requires-Dist: djangocms-picture (>=2.1.3)
Requires-Dist: djangocms-text-ckeditor (>=3.7.0)
Requires-Dist: easy-thumbnails (>=2.3)
Requires-Dist: huey (>=2.3.0)
Requires-Dist: icalendar (>=3.9.0)
Requires-Dist: intervaltree (>=2.1.0)
Requires-Dist: paypalrestsdk (>=1.12.0)
Requires-Dist: persisting-theory (>=0.2.1)
Requires-Dist: python-dateutil (>=2.4.1)
Requires-Dist: pytz (>=2017.2)
Requires-Dist: redis (>=3.1.0)
Requires-Dist: requests (>=2.6.0)
Requires-Dist: six (>=1.10.0)
Requires-Dist: squareconnect (>=2.20180712.3)
Requires-Dist: stripe (>=1.62.0)
Requires-Dist: unicodecsv (>=0.14.1)
